atj_algotrading/__init__.py
atj_algotrading/backtester/__init__.py
atj_algotrading/backtester/backtest_simulator.py
atj_algotrading/backtester/sample_backtest.ipynb
atj_algotrading/mt5_trade_utils/__init__.py
atj_algotrading/trading_bot/__init__.py
atj_algotrading_lib-0.0.6.dist-info/METADATA
atj_algotrading_lib-0.0.6.dist-info/WHEEL
atj_algotrading_lib-0.0.6.dist-info/licenses/LICENSE
atj_algotrading_lib-0.0.6.dist-info/RECORD
